JsonBoard-0.3.0.data/scripts/jsonboard
jsonboard/__init__.py
jsonboard/main.py
jsonboard/client/build/asset-manifest.json
jsonboard/client/build/favicon.ico
jsonboard/client/build/index.html
jsonboard/client/build/manifest.json
jsonboard/client/build/static/css/main.838bc5b9.css
jsonboard/client/build/static/css/main.838bc5b9.css.map
jsonboard/client/build/static/js/main.876acb88.js
jsonboard/client/build/static/js/main.876acb88.js.LICENSE.txt
jsonboard/client/build/static/js/main.876acb88.js.map
jsonboard/server/__init__.py
jsonboard/server/data.py
jsonboard/server/handler.py
jsonboard/server/server.py
JsonBoard-0.3.0.dist-info/LICENSE
JsonBoard-0.3.0.dist-info/METADATA
JsonBoard-0.3.0.dist-info/WHEEL
JsonBoard-0.3.0.dist-info/top_level.txt
JsonBoard-0.3.0.dist-info/RECORD
