Metadata-Version: 2.1
Name: JsonBoard
Version: 0.3.0
Summary: Data visualization tool based on JSON files.
Home-page: https://github.com/lucadiliello/jsonboard
Author: Luca Di Liello
Author-email: luca.diliello@unitn.it
License: UNKNOWN
Project-URL: Bug Tracker, https://github.com/lucadiliello/jsonboard/issues
Platform: UNKNOWN
License-File: LICENSE
Requires-Dist: flask (>=2)
Requires-Dist: flask-cors (>=3.0.10)
Requires-Dist: flask-restful (>=0.3.9)
